Metadata-Version: 2.1
Name: cloudflarekv
Version: 0.1.0
Summary: Super simple access to cloudflare workers kv store
Home-page: https://gitlab.com/toast38coza/cloudflarekv
Author: AppointmentGuru
Author-email: tech@appointmentguru.co
License: UNKNOWN
Platform: UNKNOWN
Classifier: Programming Language :: Python :: 3
Classifier: Operating System :: OS Independent
